{
	"credit": "Made with Blockbench",
	"parent": "generated",
	"texture_size": [256, 256],
	"textures": {
		"1": "item/babyslug"
	},
	"elements": [
		{
			"name": "base",
			"from": [5, 1, 3],
			"to": [11, 4, 18],
			"faces": {
				"north": {"uv": [5.5, 4.9375, 8.5, 5.5], "texture": "#1"},
				"east": {"uv": [5.5, 6.0625, 8.25, 6.625], "texture": "#1"},
				"south": {"uv": [5.5, 5.5, 8.5, 6.0625], "texture": "#1"},
				"west": {"uv": [2.5, 6.5, 5.25, 7.0625], "texture": "#1"},
				"up": {"uv": [3, 2.75, 0, 0], "texture": "#1"},
				"down": {"uv": [3, 2.75, 0, 5.5], "texture": "#1"}
			}
		},
		{
			"name": "chest",
			"from": [5, 4, 3],
			"to": [11, 10, 8],
			"faces": {
				"north": {"uv": [3, 0, 5.5, 1.9375], "texture": "#1"},
				"east": {"uv": [5.5, 1.0625, 6.5625, 3], "texture": "#1"},
				"south": {"uv": [3, 1.9375, 5.5, 3.875], "texture": "#1"},
				"west": {"uv": [5.5, 3, 6.5625, 4.9375], "texture": "#1"},
				"up": {"uv": [2.5, 6.5625, 0, 5.5], "texture": "#1"},
				"down": {"uv": [8, 0, 5.5, 1.0625], "texture": "#1"}
			}
		},
		{
			"name": "eye1",
			"from": [5, 10, 4],
			"to": [7, 13, 6],
			"faces": {
				"north": {"uv": [6.4375, 6.9375, 6.75, 7.4375], "texture": "#1"},
				"east": {"uv": [7, 3.5, 7.3125, 4], "texture": "#1"},
				"south": {"uv": [7, 4, 7.3125, 4.5], "texture": "#1"},
				"west": {"uv": [2.5, 7.0625, 2.8125, 7.5625], "texture": "#1"},
				"up": {"uv": [5.25, 7.375, 4.9375, 7.0625], "texture": "#1"},
				"down": {"uv": [7.375, 6.625, 7.0625, 6.9375], "texture": "#1"}
			}
		},
		{
			"name": "eye2",
			"from": [9, 10, 4],
			"to": [11, 13, 6],
			"faces": {
				"north": {"uv": [2.8125, 7.0625, 3.125, 7.5625], "texture": "#1"},
				"east": {"uv": [3.125, 7.0625, 3.4375, 7.5625], "texture": "#1"},
				"south": {"uv": [3.4375, 7.0625, 3.75, 7.5625], "texture": "#1"},
				"west": {"uv": [3.75, 7.0625, 4.0625, 7.5625], "texture": "#1"},
				"up": {"uv": [7.375, 7.25, 7.0625, 6.9375], "texture": "#1"},
				"down": {"uv": [0.3125, 7.125, 0, 7.4375], "texture": "#1"}
			}
		},
		{
			"name": "back",
			"from": [5, 4, 8],
			"to": [11, 7, 16],
			"faces": {
				"north": {"uv": [6.5625, 1.625, 9.0625, 1.9375], "texture": "#1"},
				"east": {"uv": [6.5625, 2.875, 7.875, 3.1875], "texture": "#1"},
				"south": {"uv": [6.5625, 1.9375, 9.0625, 2.25], "texture": "#1"},
				"west": {"uv": [6.5625, 3.1875, 7.875, 3.5], "texture": "#1"},
				"up": {"uv": [5.5, 5.1875, 3, 3.875], "texture": "#1"},
				"down": {"uv": [5.5, 5.1875, 3, 6.5], "texture": "#1"}
			}
		},
		{
			"name": "back2",
			"from": [5, 7, 8],
			"to": [11, 9, 13],
			"faces": {
				"north": {"uv": [6.5625, 2.25, 9.0625, 2.5625], "texture": "#1"},
				"east": {"uv": [5.6875, 6.625, 6.25, 6.9375], "texture": "#1"},
				"south": {"uv": [6.5625, 2.5625, 9.0625, 2.875], "texture": "#1"},
				"west": {"uv": [6.25, 6.625, 6.8125, 6.9375], "texture": "#1"},
				"up": {"uv": [2.5, 7.125, 0, 6.5625], "texture": "#1"},
				"down": {"uv": [9.0625, 1.0625, 6.5625, 1.625], "texture": "#1"}
			}
		},
		{
			"name": "mp1",
			"from": [5, 5, 1],
			"to": [7, 8, 3],
			"faces": {
				"north": {"uv": [2.5, 5.5, 2.9375, 6.1875], "texture": "#1"},
				"east": {"uv": [6.8125, 6.625, 7.0625, 7.3125], "texture": "#1"},
				"south": {"uv": [6.5625, 3.5, 7, 4.1875], "texture": "#1"},
				"west": {"uv": [5.6875, 6.9375, 5.9375, 7.625], "texture": "#1"},
				"up": {"uv": [2.9375, 6.4375, 2.5, 6.1875], "texture": "#1"},
				"down": {"uv": [7.4375, 4.5, 7, 4.75], "texture": "#1"}
			}
		},
		{
			"name": "mp2",
			"from": [9, 5, 1],
			"to": [11, 8, 3],
			"faces": {
				"north": {"uv": [6.5625, 4.1875, 7, 4.875], "texture": "#1"},
				"east": {"uv": [5.9375, 6.9375, 6.1875, 7.625], "texture": "#1"},
				"south": {"uv": [5.25, 6.625, 5.6875, 7.3125], "texture": "#1"},
				"west": {"uv": [6.1875, 6.9375, 6.4375, 7.625], "texture": "#1"},
				"up": {"uv": [4.5, 7.3125, 4.0625, 7.0625], "texture": "#1"},
				"down": {"uv": [4.9375, 7.0625, 4.5, 7.3125], "texture": "#1"}
			}
		}
	],
	"display": {
		"gui": {
			"rotation": [-164.25, 30.5, -180],
			"scale": [0.5, 0.5, 0.5]
		},
		"head": {
			"translation": [0, -11.25, 0],
			"scale": [4, 4, 4]
		}
	},
	"groups": [
		{
			"name": "slug",
			"origin": [8, 8, 8],
			"color": 0,
			"children": [0, 1, 2, 3, 4, 5, 6, 7]
		}
	]
}